Workbook

Sheet جرد ١٥ فبراير ٢٠٢٥
B3: مجموعة عمل الجرد مكونة من
A4: 1 | B4: الاسم
A5: 2 | B5: Hany G
A6: 3 | B6: Sony
A7: 4
A10: الكتب | C10: الرصيد الدفتري | D10: الجرد الفعلي 2025/2/15 | E10: فرق المخزون | F10: ملاحظات
A11: 1 | B11: النص الاساسى | C11: 400 | D11: 400 | E11: =D11-C11 -> 0
A12: 2 | B12: إنه يعمل - كيف ولماذا | C12: 260 | D12: 260 | E12: =D12-C12 -> 0
A13: 3 | B13: دليل العمل بالخطوات | C13: 230 | D13: 230 | E13: =D13-C13 -> 0
A14: 4 | B14: كتاب لليوم فقط | C14: 85 | D14: 103 | E14: =D14-C14 -> 18
A15: 5 | B15: الدليل التمهيدى | C15: 567 | D15: 567 | E15: =D15-C15 -> 0
A16: 6 | B16: روح تقاليدنا | C16: 183 | D16: 183 | E16: =D16-C16 -> 0
A17: 7 | B17: living clean | C17: 444 | D17: 444 | E17: =D17-C17 -> 0
A18: 8 | B18: النص الاساسى (جيب) | C18: 821 | D18: 812 | E18: =D18-C18 -> -9
A19: 9 | B19: إنة يعمل - كيف ولماذا (جيب) | C19: 0 | E19: =D19-C19 -> 0
A20: 10 | B20: دليل العمل بالخطوات (جيب) | C20: 0 | E20: =D20-C20 -> 0
A21: 11 | B21: كتاب لليوم فقط (جيب) | C21: 0 | E21: =D21-C21 -> 0
A22: 12 | B22: النص الاساسى (تذكاري) | C22: 0 | E22: =D22-C22 -> 0
A23: 13 | B23: أنة يعمل - كيف ولماذا (تذكاري) | C23: 14 | D23: 4 | E23: =D23-C23 -> -10
A24: 14 | B24: دليل عمل الخطوات (تذكاري) | C24: 9 | D24: 9 | E24: =D24-C24 -> 0
A25: 15 | B25: كتاب لليوم فقط (تذكاري) | C25: 0 | E25: =D25-C25 -> 0
A26: الكتيبات (IP)
A27: 1 | B27: للعضو الجديد | C27: 298 | D27: 300 | E27: =D27-C27 -> 2
A28: 2 | B28: هل انا مدمن | C28: 378 | D28: 374 | E28: =D28-C28 -> -4
A29: 3 | B29: مرحبا بك فى زمالة م.م. | C29: 491 | D29: 499 | E29: =D29-C29 -> 8
A30: 4 | B30: لليوم فقط | C30: 2986 | D30: 2998 | E30: =D30-C30 -> 12
A31: 5 | B31: التوجية | C31: 300 | D31: 300 | E31: =D31-C31 -> 0
A32: 6 | B32: نظرة أخرى | C32: 2901 | D32: 2899 | E32: =D32-C32 -> -2
A33: 7 | B33: التعافى والانتكاس | C33: 1668 | D33: 1670 | E33: =D33-C33 -> 2
A34: 8 | B34: تقبل الذات | C34: 1617 | D34: 1617 | E34: =D34-C34 -> 0
A35: 9 | B35: مثلث الهاجس الذاتي | C35: 382 | D35: 387 | E35: =D35-C35 -> 5
A36: 10 | B36: مقدمة لاجتماعات زمالة م.م | C36: 0 | D36: 0 | E36: =D36-C36 -> 0
A37: 11 | B37: من - ماذا - كيف ولماذا | C37: 1054 | D37: 1054 | E37: =D37-C37 -> 0
A38: 12 | B38: تجربة مدمن مع التقبل والإيمان والالتزام | C38: 1415 | D38: 1415 | E38: =D38-C38 -> 0
... A51: 25 | B51: امكانية الوصول لذوي الاحتيجات | C51: 500 | D51: 500 | E51: =D51-C51 -> 0
A52: الشيبات Chips
A53: 1 | B53: Welcome / White | C53: 0 | E53: =D53-C53 -> 0
A54: 2 | B54: 30 Days / Orange | C54: 471 | D54: 471 | E54: =D54-C54 -> 0
A55: 3 | B55: 60 Days / Green | C55: 408 | D55: 408 | E55: =D55-C55 -> 0
A56: 4 | B56: 90 Days / Red | C56: 115 | D56: 116 | E56: =D56-C56 -> 1
A57: 5 | B57: 6 Months / Blue | C57: 41 | D57: 41 | E57: =D57-C57 -> 0
A58: 6 | B58: 9 Months / Yellow | C58: 770 | D58: 772 | E58: =D58-C58 -> 2
A59: 7 | B59: 1 Year / Moonglow | C59: 14 | D59: 14 | E59: =D59-C59 -> 0
A60: 8 | B60: 18 Months / Grey | C60: 519 | D60: 520 | E60: =D60-C60 -> 1
A61: 9 | B61: Muiltple Years / Black | C61: 1 | D61: 1 | E61: =D61-C61 -> 0
A62: English Books
A63: 1 | B63: Basic Text - Reg Size | C63: 0 | E63: =D63-C63 -> 0
A64: 2 | B64: Basic Text - Pocket Size | C64: 3 | D64: 3 | E64: =D64-C64 -> 0
A65: 3 | B65: Basic Text - Gift Edition | C65: 7 | D65: 7 | E65: =D65-C65 -> 0
A66: 4 | B66: JFT - Reg Size | C66: 2 | D66: 2 | E66: =D66-C66 -> 0
A67: 5 | B67: JFT - Pocket Size | C67: 2 | D67: 2 | E67: =D67-C67 -> 0
A68: 6 | B68: JFT - Gift Edition | C68: 0 | D68: 0 | E68: =D68-C68 -> 0
A69: 7 | B69: How & Why - Reg Size | C69: 0 | D69: 0 | E69: =D69-C69 -> 0
A70: 8 | B70: How & Why - Pocket Size | C70: 6 | D70: 6 | E70: =D70-C70 -> 0
A71: 9 | B71: Sponsorship | C71: 32 | D71: 32 | E71: =D71-C71 -> 0
A72: 10 | B72: Sponsorship - Gift Edition | C72: 10 | D72: 10 | E72: =D72-C72 -> 0
A73: 11 | B73: Step Working Guide | C73: 0 | D73: 0 | E73: =D73-C73 -> 0
A74: 12 | B74: Introductory Guide to NA | C74: 0 | D74: 0 | E74: =D74-C74 -> 0
A75: 13 | B75: Living Clean | C75: 5 | D75: 5 | E75: =D75-C75 -> 0
... A83: 21 | B83: The Basic Library | C83: 0 | D83: 0 | E83: =D83-C83 -> 0
A84: English IP (s)
A85: 1 | B85: For the Newcomer | C85: 36 | D85: 30 | E85: =D85-C85 -> -6
A86: 2 | B86: Welcome to NA | C86: 34 | D86: 40 | E86: =D86-C86 -> 6
A87: 3 | B87: A resource in your community | C87: 12 | D87: 12 | E87: =D87-C87 -> 0
A88: 4 | B88: Accessibility for Those with Additional Needs | C88: 26 | D88: 26 | E88: =D88-C88 -> 0
A89: 5 | B89: Am I an Addict ? | C89: 44 | D89: 43 | E89: =D89-C89 -> -1
A90: 6 | B90: Another Look | C90: 57 | D90: 57 | E90: =D90-C90 -> 0
A91: 7 | B91: Behind the Walls | C91: 11 | D91: 11 | E91: =D91-C91 -> 0
A92: 8 | B92: By Young Addicts for Young Addicts | C92: 17 | D92: 17 | E92: =D92-C92 -> 0
A93: 9 | B93: Disruptive & Violent | C93: 18 | D93: 18 | E93: =D93-C93 -> 0
A94: 10 | B94: For the Parents or Guardians of Young People in NA | C94: 52 | D94: 52 | E94: =D94-C94 -> 0
A95: 11 | B95: For Those in Treatment | C95: 92 | D95: 92 | E95: =D95-C95 -> 0
A96: 12 | B96: Funding NA Services | C96: 44 | D96: 44 | E96: =D96-C96 -> 0
... A122: 38 | B122: mental health in recovery | C122: 30 | D122: 30 | E122: =D122-C122 -> 0
A123: Readings القراءات
A124: 1 | B124: مجموعة قراءات (عربي) | C124: 3 | D124: 2 | E124: =D124-C124 -> -1 | F124: one at printing house
A125: 2 | B125: مجموعة قراءات (انجليزي) | C125: 1 | D125: 9 | E125: =D125-C125 -> 8 | F125: one at printing house
A126: Medals & Coins
A127: 1 | B127: كوين سنة برونز | C127: 14 | D127: 14 | E127: =D127-C127 -> 0
A128: 2 | B128: كوين سنة ونصف برونز | C128: 25 | D128: 25 | E128: =D128-C128 -> 0
A129: 3 | B129: كوين سنتان برونز | C129: 22 | D129: 22 | E129: =D129-C129 -> 0
A130: 4 | B130: كوين 3 سنين برونز | C130: 29 | D130: 29 | E130: =D130-C130 -> 0
A131: 5 | B131: كوين 4 سنوات برونز | C131: 17 | D131: 17 | E131: =D131-C131 -> 0
A132: 6 | B132: كوين 5 سنوات برونز | C132: 29 | D132: 29 | E132: =D132-C132 -> 0
A133: 7 | B133: كوين 6 سنوات برونز | C133: 43 | D133: 43 | E133: =D133-C133 -> 0
A134: 8 | B134: كوين 7 سنوات برونز | C134: 60 | D134: 60 | E134: =D134-C134 -> 0
A135: 9 | B135: كوين 8 سنوات برونز | C135: 62 | D135: 62 | E135: =D135-C135 -> 0
A136: 10 | B136: كوين 9 سنوات برونز | C136: 53 | D136: 53 | E136: =D136-C136 -> 0
A137: 11 | B137: كوين 10 سنوات برونز | C137: 17 | D137: 17 | E137: =D137-C137 -> 0
A138: 12 | B138: كوين 11 سنة برونز | C138: 13 | D138: 13 | E138: =D138-C138 -> 0
... A204: 78 | B204: ميداية مجمعة موجه | C204: 7 | D204: 7 | E204: =D204-C204 -> 0

Sheet جرد ١٣ أغسطس ٢٠٢٥ مع الملاحظات
B2: مجموعة عمل الجرد مكونة من
B3: الاسم | C3: المنصب الخدمي
A4: 1 | B4: وليد | C4: امين صندوق الإقليم
A5: 2 | B5: كريم | C5: رئيس لجنة الادبيات
A6: 3 | B6: رامي | C6: شمال شرق RCM
A7: 4 | B7: سوني | C7: امين مخزن
A9: الكتب | C9: الرصيد الدفتري | D9: الجرد الفعلي 2025/8/13 | E9: فرق المخزون | F9: ملاحظات
A10: 1 | B10: النص الاساسى | C10: 20 | D10: 20 | E10: =D10-C10 -> 0
A11: 2 | B11: إنه يعمل - كيف ولماذا | C11: 90 | D11: 90 | E11: =D11-C11 -> 0
A12: 3 | B12: دليل العمل بالخطوات | C12: 60 | D12: 60 | E12: =D12-C12 -> 0
A13: 4 | B13: كتاب لليوم فقط | C13: 0 | D13: 0 | E13: =D13-C13 -> 0
A14: 5 | B14: الدليل التمهيدى | C14: 557 | D14: 557 | E14: =D14-C14 -> 0
A15: 6 | B15: روح تقاليدنا | C15: 73 | D15: 73 | E15: =D15-C15 -> 0
A16: 7 | B16: living clean | C16: 334 | D16: 334 | E16: =D16-C16 -> 0
A17: 8 | B17: النص الاساسى (جيب) | C17: 662 | D17: 662 | E17: =D17-C17 -> 0
A18: 9 | B18: إنة يعمل - كيف ولماذا (جيب) | C18: 0 | E18: =D18-C18 -> 0
A19: 10 | B19: دليل العمل بالخطوات (جيب) | C19: 0 | E19: =D19-C19 -> 0
A20: 11 | B20: كتاب لليوم فقط (جيب) | C20: 0 | E20: =D20-C20 -> 0
A21: 12 | B21: النص الاساسى (تذكاري) | C21: 0 | E21: =D21-C21 -> 0
A22: 13 | B22: أنة يعمل - كيف ولماذا (تذكاري) | C22: 0 | D22: 4 | E22: =D22-C22 -> 4 | F22: العدد مظبو ط تم تعديل الاعداد حسب نوع الكتباب
A23: 14 | B23: دليل عمل الخطوات (تذكاري) | C23: 13 | D23: 9 | E23: =D23-C23 -> -4
A24: 15 | B24: كتاب لليوم فقط (تذكاري) | C24: 0 | E24: =D24-C24 -> 0
A25: الكتيبات (IP)
A26: 1 | B26: للعضو الجديد | C26: 48 | D26: 48 | E26: =D26-C26 -> 0
A27: 2 | B27: هل انا مدمن | C27: 0 | E27: =D27-C27 -> 0
A28: 3 | B28: مرحبا بك فى زمالة م.م. | C28: 149 | D28: 150 | E28: =D28-C28 -> 1
A29: 4 | B29: لليوم فقط | C29: 2948 | D29: 2927 | E29: =D29-C29 -> -21 | F29: فرق جرد ١٥ فبراير ٢٠٢٥ ليس عليه حركة و تم تعديل العدد
A30: 5 | B30: التوجية | C30: 0 | E30: =D30-C30 -> 0
A31: 6 | B31: نظرة أخرى | C31: 2799 | D31: 2799 | E31: =D31-C31 -> 0
A32: 7 | B32: التعافى والانتكاس | C32: 1670 | D32: 1668 | E32: =D32-C32 -> -2 | F32: فرق جرد ١٥ فبراير ٢٠٢٥ ليس عليه حركة و تم تعديل العدد
A33: 8 | B33: تقبل الذات | C33: 1617 | D33: 1617 | E33: =D33-C33 -> 0
A34: 9 | B34: مثلث الهاجس الذاتي | C34: 387 | D34: 387 | E34: =D34-C34 -> 0
A35: 10 | B35: مقدمة لاجتماعات زمالة م.م | C35: 0 | E35: =D35-C35 -> 0
A36: 11 | B36: من - ماذا - كيف ولماذا | C36: 1054 | D36: 1054 | E36: =D36-C36 -> 0
A37: 12 | B37: تجربة مدمن مع التقبل والإيمان والالتزام | C37: 1415 | D37: 1415 | E37: =D37-C37 -> 0
A38: 13 | B38: البقاء ممتنعا في الخارج | C38: 1900 | D38: 1900 | E38: =D38-C38 -> 0
A39: 14 | B39: رسالة لمن هم بالمصحات | C39: 655 | D39: 655 | E39: =D39-C39 -> 0
A40: 15 | B40: التواصل الاجتماعى | C40: 300 | D40: 300 | E40: =D40-C40 -> 0
A41: 16 | B41: الخدم الموثوق بهم | C41: 500 | D41: 500 | E41: =D41-C41 -> 0
A42: 17 | B42: الامور المالية | C42: 450 | D42: 450 | E42: =D42-C42 -> 0
A43: 18 | B43: تمويل الخدمات | C43: 490 | D43: 490 | E43: =D43-C43 -> 0
A44: 19 | B44: السلوك المعيق | C44: 1391 | D44: 1391 | E44: =D44-C44 -> 0
A45: 20 | B45: المجموعة | C45: 80 | D45: 80 | E45: =D45-C45 -> 0
A46: 21 | B46: معايشة البرنامج | C46: 400 | D46: 400 | E46: =D46-C46 -> 0
A47: 22 | B47: المنعزل - البقاء ممتنعاً | C47: 544 | D47: 544 | E47: =D47-C47 -> 0
... A50: 25 | B50: امكانية الوصول لذوي الاحتيجات | C50: 400 | D50: 400 | E50: =D50-C50 -> 0
A51: الشيبات Chips
A52: 1 | B52: Welcome / White | C52: 1 | D52: 1 | E52: =D52-C52 -> 0
A53: 2 | B53: 30 Days / Orange | C53: 227 | D53: 227 | E53: =D53-C53 -> 0
A54: 3 | B54: 60 Days / Green | C54: 169 | D54: 169 | E54: =D54-C54 -> 0
A55: 4 | B55: 90 Days / Red | C55: 18 | D55: 18 | E55: =D55-C55 -> 0
A56: 5 | B56: 6 Months / Blue | C56: 0 | D56: 0 | E56: =D56-C56 -> 0
A57: 6 | B57: 9 Months / Yellow | C57: 449 | D57: 449 | E57: =D57-C57 -> 0
A58: 7 | B58: 1 Year / Moonglow | C58: 14 | D58: 14 | E58: =D58-C58 -> 0
A59: 8 | B59: 18 Months / Grey | C59: 309 | D59: 309 | E59: =D59-C59 -> 0
A60: 9 | B60: Muiltple Years / Black | C60: 24 | D60: 24 | E60: =D60-C60 -> 0
A61: English Books
A62: 1 | B62: Basic Text - Reg Size | C62: 3 | D62: 3 | E62: =D62-C62 -> 0
A63: 2 | B63: Basic Text - Pocket Size | C63: 2 | D63: 2 | E63: =D63-C63 -> 0
A64: 3 | B64: Basic Text - Gift Edition | C64: 0 | E64: =D64-C64 -> 0
A65: 4 | B65: JFT - Reg Size | C65: 2 | D65: 2 | E65: =D65-C65 -> 0
A66: 5 | B66: JFT - Pocket Size | C66: 0 | E66: =D66-C66 -> 0
A67: 6 | B67: JFT - Gift Edition | C67: 0 | E67: =D67-C67 -> 0
A68: 7 | B68: How & Why - Reg Size | C68: 2 | D68: 2 | E68: =D68-C68 -> 0
A69: 8 | B69: How & Why - Pocket Size | C69: 4 | D69: 4 | E69: =D69-C69 -> 0
A70: 9 | B70: Sponsorship | C70: 23 | D70: 23 | E70: =D70-C70 -> 0
A71: 10 | B71: Sponsorship - Gift Edition | C71: 7 | D71: 7 | E71: =D71-C71 -> 0
A72: 11 | B72: Step Working Guide | C72: 2 | D72: 2 | E72: =D72-C72 -> 0
A73: 12 | B73: Introductory Guide to NA | C73: 5 | D73: 5 | E73: =D73-C73 -> 0
A74: 13 | B74: Living Clean | C74: 2 | D74: 2 | E74: =D74-C74 -> 0
A75: 14 | B75: Guiding Principle | C75: 7 | D75: 6 | E75: =D75-C75 -> -1 | F75: كتاب موجود في لجنة الادبيات تم التعديل من لجنة الادبيات باستلامه بتاريخ ٢٥ أغسطس ٢٠٢٥
A76: 15 | B76: Spiritual Principle A Day | C76: 21 | D76: 21 | E76: =D76-C76 -> 0
A77: 16 | B77: Miracle Happens Hard | C77: 0 | E77: =D77-C77 -> 0
A78: 17 | B78: Commemorative Living Clean | C78: 0 | E78: =D78-C78 -> 0
A79: 18 | B79: Guiding Principles Special Edition | C79: 0 | E79: =D79-C79 -> 0
A80: 19 | B80: SPAD Special Edition | C80: 0 | E80: =D80-C80 -> 0
A81: 20 | B81: JFT Journal | C81: 0 | E81: =D81-C81 -> 0
A82: 21 | B82: The Basic Library | C82: 0 | E82: =D82-C82 -> 0
A83: English IP (s)
A84: 1 | B84: For the Newcomer | C84: 40 | D84: 40 | E84: =D84-C84 -> 0
A85: 2 | B85: Welcome to NA | C85: 20 | D85: 20 | E85: =D85-C85 -> 0
A86: 3 | B86: A resource in your community | C86: 2 | D86: 2 | E86: =D86-C86 -> 0
A87: 4 | B87: Accessibility for Those with Additional Needs | C87: 16 | D87: 16 | E87: =D87-C87 -> 0
A88: 5 | B88: Am I an Addict ? | C88: 23 | D88: 24 | E88: =D88-C88 -> 1 | F88: فرق جرد ١٥ فبراير ٢٠٢٥ ليس عليه حركة و تم تعديل العدد
A89: 6 | B89: Another Look | C89: 47 | D89: 47 | E89: =D89-C89 -> 0
A90: 7 | B90: Behind the Walls | C90: 10 | D90: 10 | E90: =D90-C90 -> 0
A91: 8 | B91: By Young Addicts for Young Addicts | C91: 7 | D91: 7 | E91: =D91-C91 -> 0
A92: 9 | B92: Disruptive & Violent | C92: 8 | D92: 7 | E92: =D92-C92 -> -1 | F92: فرق جرد ١٥ فبراير ٢٠٢٥ ليس عليه حركة و تم تعديل العدد
A93: 10 | B93: For the Parents or Guardians of Young People in NA | C93: 42 | D93: 42 | E93: =D93-C93 -> 0
A94: 11 | B94: For Those in Treatment | C94: 72 | D94: 72 | E94: =D94-C94 -> 0
A95: 12 | B95: Funding NA Services | C95: 44 | D95: 44 | E95: =D95-C95 -> 0
A96: 13 | B96: Group Business | C96: 9 | D96: 8 | E96: =D96-C96 -> -1 | F96: سوف يتم مراجعة الاستلامات
A97: 14 | B97: Hospitals and Institutions Service and the NA member | C97: 48 | D97: 49 | E97: =D97-C97 -> 1
A98: 15 | B98: In Time of Illness | C98: 0 | D98: 0 | E98: =D98-C98 -> 0
A99: 16 | B99: Introduction to NA Meetings | C99: 48 | D99: 48 | E99: =D99-C99 -> 0
A100: 17 | B100: Just For Today (IP) | C100: 110 | D100: 110 | E100: =D100-C100 -> 0
A101: 18 | B101: Living the program | C101: 40 | D101: 40 | E101: =D101-C101 -> 0
A102: 19 | B102: Money Matters Self-Support in NA | C102: 41 | D102: 41 | E102: =D102-C102 -> 0
A103: 20 | B103: NA Groups & Medication | C103: 134 | D103: 134 | E103: =D103-C103 -> 0
A104: 21 | B104: One Addict’s Experience with Acceptance, Faith, and Commitment | C104: 39 | D104: 39 | E104: =D104-C104 -> 0
...

Sheet العهدة الحالية
A3: الكتب | C3: رصيد البداية 12 -6- 2026 | D3: إجمالي الصادر | E3: إجمالي الوارد | F3: الرصيد الحالي | G3: سعر البيع | H3: مجموع المخزون / جنيه مصري | I3: متوسط الإستهلاك الشهري | J3: الاستهلاك السنوي للأدبيات الإنجليزية | K3: كمية تكفي 4 شهور | L3: الفرق عن الحد الأدني
A4: 1 | B4: النص الاساسى | C4: 255 | D4: ='الصادر بعد الجرد'!Y4 -> 150 | E4: ='الوارد بعد الجرد'!AC4 -> 100 | F4: =C4-D4+E4 -> 205 | G4: 75 | H4: =G4*F4 -> 15375 | I4: 213 | K4: =I4*4 -> 852 | L4: =F4-K4 -> -647
A5: 2 | B5: إنه يعمل - كيف ولماذا | C5: 355 | D5: ='الصادر بعد الجرد'!Y5 -> 50 | E5: ='الوارد بعد الجرد'!AC5 -> 0 | F5: =C5-D5+E5 -> 305 | G5: 160 | H5: =G5*F5 -> 48800 | I5: 88 | K5: =I5*4 -> 352 | L5: =F5-K5 -> -47
A6: 3 | B6: دليل العمل بالخطوات | C6: 100 | D6: ='الصادر بعد الجرد'!Y6 -> 150 | E6: ='الوارد بعد الجرد'!AC6 -> 150 | F6: =C6-D6+E6 -> 100 | G6: 150 | H6: =G6*F6 -> 15000 | I6: 82 | K6: =I6*4 -> 328 | L6: =F6-K6 -> -228
A7: 4 | B7: كتاب لليوم فقط | C7: 525 | D7: ='الصادر بعد الجرد'!Y7 -> 40 | E7: ='الوارد بعد الجرد'!AC7 -> 0 | F7: =C7-D7+E7 -> 485 | G7: 100 | H7: =G7*F7 -> 48500 | K7: =I7*4 -> 0 | L7: =F7-K7 -> 485
A8: 5 | B8: الدليل التمهيدى | C8: 377 | D8: ='الصادر بعد الجرد'!Y8 -> 0 | E8: ='الوارد بعد الجرد'!AC8 -> 0 | F8: =C8-D8+E8 -> 377 | G8: 55 | H8: =G8*F8 -> 20735 | I8: 62 | K8: =I8*4 -> 248 | L8: =F8-K8 -> 129
A9: 6 | B9: روح تقاليدنا | C9: 907 | D9: ='الصادر بعد الجرد'!Y9 -> 40 | E9: ='الوارد بعد الجرد'!AC9 -> 0 | F9: =C9-D9+E9 -> 867 | G9: 130 | H9: =G9*F9 -> 112710 | K9: =I9*4 -> 0 | L9: =F9-K9 -> 867
A10: 7 | B10: living clean | C10: 940 | D10: ='الصادر بعد الجرد'!Y10 -> 60 | E10: ='الوارد بعد الجرد'!AC10 -> 0 | F10: =C10-D10+E10 -> 880 | G10: 85 | H10: =G10*F10 -> 74800 | K10: =I10*4 -> 0 | L10: =F10-K10 -> 880
A11: 8 | B11: النص الاساسى (جيب) | D11: ='الصادر بعد الجرد'!Y11 -> 0 | E11: ='الوارد بعد الجرد'!AC11 -> 0 | F11: =C11-D11+E11 -> 0 | G11: 25 | H11: =G11*F11 -> 0 | I11: 12 | K11: =I11*4 -> 48 | L11: =F11-K11 -> -48
A12: 9 | B12: إنة يعمل - كيف ولماذا (جيب) | D12: ='الصادر بعد الجرد'!Y12 -> 0 | E12: ='الوارد بعد الجرد'!AC12 -> 0 | F12: =C12-D12+E12 -> 0 | H12: =G12*F12 -> 0 | K12: =I12*4 -> 0 | L12: =F12-K12 -> 0
A13: 10 | B13: دليل العمل بالخطوات (جيب) | D13: ='الصادر بعد الجرد'!Y13 -> 0 | E13: ='الوارد بعد الجرد'!AC13 -> 0 | F13: =C13-D13+E13 -> 0 | H13: =G13*F13 -> 0 | K13: =I13*4 -> 0 | L13: =F13-K13 -> 0
A14: 11 | B14: كتاب لليوم فقط (جيب) | D14: ='الصادر بعد الجرد'!Y14 -> 0 | E14: ='الوارد بعد الجرد'!AC14 -> 0 | F14: =C14-D14+E14 -> 0 | H14: =G14*F14 -> 0 | K14: =I14*4 -> 0 | L14: =F14-K14 -> 0
A15: 12 | B15: النص الاساسى (تذكاري) | D15: ='الصادر بعد الجرد'!Y15 -> 0 | E15: ='الوارد بعد الجرد'!AC15 -> 0 | F15: =C15-D15+E15 -> 0 | G15: 150 | H15: =G15*F15 -> 0 | K15: =I15*4 -> 0 | L15: =F15-K15 -> 0
A16: 13 | B16: أنة يعمل - كيف ولماذا (تذكاري) | C16: 4 | D16: ='الصادر بعد الجرد'!Y16 -> 0 | E16: ='الوارد بعد الجرد'!AC16 -> 0 | F16: =C16-D16+E16 -> 4 | G16: 250 | H16: =G16*F16 -> 1000 | K16: =I16*4 -> 0 | L16: =F16-K16 -> 4
A17: 14 | B17: دليل عمل الخطوات (تذكاري) | C17: 4 | D17: ='الصادر بعد الجرد'!Y17 -> 0 | E17: ='الوارد بعد الجرد'!AC17 -> 0 | F17: =C17-D17+E17 -> 4 | G17: 240 | H17: =G17*F17 -> 960 | K17: =I17*4 -> 0 | L17: =F17-K17 -> 4
A18: 15 | B18: كتاب لليوم فقط (تذكاري) | D18: ='الصادر بعد الجرد'!Y18 -> 0 | E18: ='الوارد بعد الجرد'!AC18 -> 0 | F18: =C18-D18+E18 -> 0 | G18: 260 | H18: =G18*F18 -> 0 | K18: =I18*4 -> 0 | L18: =F18-K18 -> 0
B19: الكتيبات (IP)
A20: 1 | B20: للعضو الجديد | C20: 1248 | D20: ='الصادر بعد الجرد'!Y20 -> 248 | E20: ='الوارد بعد الجرد'!AC20 -> 0 | F20: =C20-D20+E20 -> 1000 | G20: 4 | H20: =G20*F20 -> 4000 | I20: 200 | K20: =I20*4 -> 800 | L20: =F20-K20 -> 200
A21: 2 | B21: هل انا مدمن | D21: ='الصادر بعد الجرد'!Y21 -> 500 | E21: ='الوارد بعد الجرد'!AC21 -> 500 | F21: =C21-D21+E21 -> 0 | G21: 4 | H21: =G21*F21 -> 0 | I21: 63 | K21: =I21*4 -> 252 | L21: =F21-K21 -> -252
A22: 3 | B22: مرحبا بك فى زمالة م.م. | C22: 100 | D22: ='الصادر بعد الجرد'!Y22 -> 100 | E22: ='الوارد بعد الجرد'!AC22 -> 0 | F22: =C22-D22+E22 -> 0 | G22: 4 | H22: =G22*F22 -> 0 | I22: 63 | K22: =I22*4 -> 252 | L22: =F22-K22 -> -252
A23: 4 | B23: لليوم فقط | C23: 1426 | D23: ='الصادر بعد الجرد'!Y23 -> 0 | E23: ='الوارد بعد الجرد'!AC23 -> 0 | F23: 1726 | G23: 4 | H23: =G23*F23 -> 6904 | I23: 10 | K23: =I23*4 -> 40 | L23: =F23-K23 -> 1686
A24: 5 | B24: التوجية | C24: 401 | D24: ='الصادر بعد الجرد'!Y24 -> 500 | E24: ='الوارد بعد الجرد'!AC24 -> 500 | F24: =C24-D24+E24 -> 401 | G24: 4 | H24: =G24*F24 -> 1604 | I24: 102 | K24: =I24*4 -> 408 | L24: =F24-K24 -> -7
A25: 6 | B25: نظرة أخرى | C25: 2124 | D25: ='الصادر بعد الجرد'!Y25 -> 0 | E25: ='الوارد بعد الجرد'!AC25 -> 0 | F25: =C25-D25+E25 -> 2124 | G25: 4 | H25: =G25*F25 -> 8496 | I25: 2 | K25: =I25*4 -> 8 | L25: =F25-K25 -> 2116
A26: 7 | B26: التعافى والانتكاس | C26: 967 | D26: ='الصادر بعد الجرد'!Y26 -> 0 | E26: ='الوارد بعد الجرد'!AC26 -> 0 | F26: =C26-D26+E26 -> 967 | G26: 4 | H26: =G26*F26 -> 3868 | I26: 11 | K26: =I26*4 -> 44 | L26: =F26-K26 -> 923
A27: 8 | B27: تقبل الذات | C27: 529 | D27: ='الصادر بعد الجرد'!Y27 -> 0 | E27: ='الوارد بعد الجرد'!AC27 -> 0 | F27: =C27-D27+E27 -> 529 | G27: 4 | H27: =G27*F27 -> 2116 | I27: 12 | K27: =I27*4 -> 48 | L27: =F27-K27 -> 481
A28: 9 | B28: مثلث الهاجس الذاتي | C28: 400 | D28: ='الصادر بعد الجرد'!Y28 -> 0 | E28: ='الوارد بعد الجرد'!AC28 -> 0 | F28: =C28-D28+E28 -> 400 | G28: 4 | H28: =G28*F28 -> 1600 | I28: 5 | K28: =I28*4 -> 20 | L28: =F28-K28 -> 380
A29: 10 | B29: مقدمة لاجتماعات زمالة م.م | C29: 3100 | D29: ='الصادر بعد الجرد'!Y29 -> 0 | E29: ='الوارد بعد الجرد'!AC29 -> 0 | F29: =C29-D29+E29 -> 3100 | G29: 4 | H29: =G29*F29 -> 12400 | I29: 10 | K29: =I29*4 -> 40 | L29: =F29-K29 -> 3060
A30: 11 | B30: من - ماذا - كيف ولماذا | C30: 375 | D30: ='الصادر بعد الجرد'!Y30 -> 0 | E30: ='الوارد بعد الجرد'!AC30 -> 0 | F30: =C30-D30+E30 -> 375 | G30: 4 | H30: =G30*F30 -> 1500 | I30: 5 | K30: =I30*4 -> 20 | L30: =F30-K30 -> 355
A31: 12 | B31: تجربة مدمن مع التقبل والإيمان والالتزام | C31: 850 | D31: ='الصادر بعد الجرد'!Y31 -> 0 | E31: ='الوارد بعد الجرد'!AC31 -> 0 | F31: =C31-D31+E31 -> 850 | G31: 4 | H31: =G31*F31 -> 3400 | I31: 4 | K31: =I31*4 -> 16 | L31: =F31-K31 -> 834
A32: 13 | B32: البقاء ممتنعا في الخارج | C32: 345 | D32: ='الصادر بعد الجرد'!Y32 -> 0 | E32: ='الوارد بعد الجرد'!AC32 -> 0 | F32: =C32-D32+E32 -> 345 | G32: 4 | H32: =G32*F32 -> 1380 | I32: 1 | K32: =I32*4 -> 4 | L32: =F32-K32 -> 341
A33: 14 | B33: رسالة لمن هم بالمصحات | C33: 575 | D33: ='الصادر بعد الجرد'!Y33 -> 0 | E33: ='الوارد بعد الجرد'!AC33 -> 0 | F33: =C33-D33+E33 -> 575 | G33: 4 | H33: =G33*F33 -> 2300 | I33: 1 | K33: =I33*4 -> 4 | L33: =F33-K33 -> 571
A34: 15 | B34: التواصل الاجتماعى | C34: 200 | D34: ='الصادر بعد الجرد'!Y34 -> 0 | E34: ='الوارد بعد الجرد'!AC34 -> 0 | F34: =C34-D34+E34 -> 200 | G34: 4 | H34: =G34*F34 -> 800 | I34: 1 | K34: =I34*4 -> 4 | L34: =F34-K34 -> 196
A35: 16 | B35: الخدم الموثوق بهم | C35: 390 | D35: ='الصادر بعد الجرد'!Y35 -> 0 | E35: ='الوارد بعد الجرد'!AC35 -> 0 | F35: =C35-D35+E35 -> 390 | G35: 4 | H35: =G35*F35 -> 1560 | I35: 1 | K35: =I35*4 -> 4 | L35: =F35-K35 -> 386
... A43: 24 | B43: للآباء أو أولياء أمور المدمنين الشباب | C43: 100 | D43: ='الصادر بعد الجرد'!Y43 -> 0 | E43: ='الوارد بعد الجرد'!AC43 -> 0 | F43: =C43-D43+E43 -> 100 | G43: 4 | H43: =G43*F43 -> 400 | I43: 1 | K43: =I43*4 -> 4 | L43: =F43-K43 -> 96
A44: 25 | B44: امكانية الوصول لذوي الاحتيجات | C44: 380 | D44: ='الصادر بعد الجرد'!Y44 -> 0 | E44: ='الوارد بعد الجرد'!AC44 -> 0 | F44: =C44-D44+E44 -> 380 | G44: 4 | H44: =G44*F44 -> 1520 | K44: =I44*4 -> 0 | L44: =F44-K44 -> 380
B46: الشيبات Chips
A47: 1 | B47: Welcome / White | C47: 0 | D47: ='الصادر بعد الجرد'!Y47 -> 0 | E47: ='الوارد بعد الجرد'!AC47 -> 0 | F47: =C47-D47+E47 -> 0 | G47: 20 | H47: =G47*F47 -> 0 | I47: 251 | K47: =I47*4 -> 1004 | L47: =F47-K47 -> -1004
A48: 2 | B48: 30 Days / Orange | C48: 906 | D48: ='الصادر بعد الجرد'!Y48 -> 200 | E48: ='الوارد بعد الجرد'!AC48 -> 0 | F48: =C48-D48+E48 -> 706 | G48: 20 | H48: =G48*F48 -> 14120 | I48: 116 | K48: =I48*4 -> 464 | L48: =F48-K48 -> 242
A49: 3 | B49: 60 Days / Green | C49: 865 | D49: ='الصادر بعد الجرد'!Y49 -> 200 | E49: ='الوارد بعد الجرد'!AC49 -> 0 | F49: =C49-D49+E49 -> 665 | G49: 20 | H49: =G49*F49 -> 13300 | I49: 132 | K49: =I49*4 -> 528 | L49: =F49-K49 -> 137
A50: 4 | B50: 90 Days / Red | C50: 571 | D50: ='الصادر بعد الجرد'!Y50 -> 200 | E50: ='الوارد بعد الجرد'!AC50 -> 0 | F50: =C50-D50+E50 -> 371 | G50: 20 | H50: =G50*F50 -> 7420 | I50: 167 | K50: =I50*4 -> 668 | L50: =F50-K50 -> -297
A51: 5 | B51: 6 Months / Blue | C51: 498 | D51: ='الصادر بعد الجرد'!Y51 -> 200 | E51: ='الوارد بعد الجرد'!AC51 -> 0 | F51: =C51-D51+E51 -> 298 | G51: 20 | H51: =G51*F51 -> 5960 | I51: 148 | K51: =I51*4 -> 592 | L51: =F51-K51 -> -294
A52: 6 | B52: 9 Months / Yellow | C52: 1318 | D52: ='الصادر بعد الجرد'!Y52 -> 200 | E52: ='الوارد بعد الجرد'!AC52 -> 0 | F52: =C52-D52+E52 -> 1118 | G52: 20 | H52: =G52*F52 -> 22360 | I52: 114 | K52: =I52*4 -> 456 | L52: =F52-K52 -> 662
A53: 7 | B53: 1 Year / Moonglow | C53: 906 | D53: ='الصادر بعد الجرد'!Y53 -> 200 | E53: ='الوارد بعد الجرد'!AC53 -> 0 | F53: =C53-D53+E53 -> 706 | G53: 20 | H53: =G53*F53 -> 14120 | I53: 108 | K53: =I53*4 -> 432 | L53: =F53-K53 -> 274
A54: 8 | B54: 18 Months / Grey | C54: 1289 | D54: ='الصادر بعد الجرد'!Y54 -> 200 | E54: ='الوارد بعد الجرد'!AC54 -> 0 | F54: =C54-D54+E54 -> 1089 | G54: 20 | H54: =G54*F54 -> 21780 | I54: 66 | K54: =I54*4 -> 264 | L54: =F54-K54 -> 825
A55: 9 | B55: Muiltple Years / Black | C55: 138 | D55: ='الصادر بعد الجرد'!Y55 -> 138 | E55: ='الوارد بعد الجرد'!AC55 -> 0 | F55: =C55-D55+E55 -> 0 | G55: 20 | H55: =G55*F55 -> 0 | I55: 146 | K55: =I55*4 -> 584 | L55: =F55-K55 -> -584
B57: Name Key Tag to be sold at event
B58: Name tag Welcome / White | C58: 197 | D58: ='الصادر بعد الجرد'!Y58 -> 0 | E58: ='الوارد بعد الجرد'!AC58 -> 0 | F58: =C58-D58+E58 -> 197 | G58: 40 | H58: =G58*F58 -> 7880
B59: Name tag 30 Days / Orange | C59: 205 | D59: ='الصادر بعد الجرد'!Y59 -> 0 | E59: ='الوارد بعد الجرد'!AC59 -> 0 | F59: =C59-D59+E59 -> 205 | G59: 40 | H59: =G59*F59 -> 8200
B60: Name tag 60 Days / Green | C60: 208 | D60: ='الصادر بعد الجرد'!Y60 -> 0 | E60: ='الوارد بعد الجرد'!AC60 -> 0 | F60: =C60-D60+E60 -> 208 | G60: 40 | H60: =G60*F60 -> 8320
B61: Name tag 90 Days / Red | C61: 200 | D61: ='الصادر بعد الجرد'!Y61 -> 0 | E61: ='الوارد بعد الجرد'!AC61 -> 0 | F61: =C61-D61+E61 -> 200 | G61: 40 | H61: =G61*F61 -> 8000
B62: Name tag 6 Months / Blue | C62: 204 | D62: ='الصادر بعد الجرد'!Y62 -> 0 | E62: ='الوارد بعد الجرد'!AC62 -> 0 | F62: =C62-D62+E62 -> 204 | G62: 40 | H62: =G62*F62 -> 8160
B63: Name tag 9 Months / Yellow | C63: 206 | D63: ='الصادر بعد الجرد'!Y63 -> 0 | E63: ='الوارد بعد الجرد'!AC63 -> 0 | F63: =C63-D63+E63 -> 206 | G63: 40 | H63: =G63*F63 -> 8240
B64: Name tag 1 Year / Moonglow | C64: 198 | D64: ='الصادر بعد الجرد'!Y64 -> 0 | E64: ='الوارد بعد الجرد'!AC64 -> 0 | F64: =C64-D64+E64 -> 198 | G64: 40 | H64: =G64*F64 -> 7920
B65: Name tag 18 Months / Grey | C65: 202 | D65: ='الصادر بعد الجرد'!Y65 -> 0 | E65: ='الوارد بعد الجرد'!AC65 -> 0 | F65: =C65-D65+E65 -> 202 | G65: 40 | H65: =G65*F65 -> 8080
B66: Name tag Muiltple Years / Black | C66: 201 | D66: ='الصادر بعد الجرد'!Y66 -> 0 | E66: ='الوارد بعد الجرد'!AC66 -> 0 | F66: =C66-D66+E66 -> 201 | G66: 40 | H66: =G66*F66 -> 8040
B68: English Books
A69: 1 | B69: Basic Text - Reg Size | C69: 28 | D69: ='الصادر بعد الجرد'!Y69 -> 0 | E69: ='الوارد بعد الجرد'!AC69 -> 0 | F69: =C69-D69+E69 -> 28 | G69: 540 | H69: =G69*F69 -> 15120 | J69: 25 | K69: =J69/4 -> 6.25 | L69: =F69-K69 -> 21.75
A70: 2 | B70: Basic Text - Pocket Size | D70: ='الصادر بعد الجرد'!Y70 -> 0 | E70: ='الوارد بعد الجرد'!AC70 -> 0 | F70: =C70-D70+E70 -> 0 | G70: 540 | H70: =G70*F70 -> 0 | J70: 5 | K70: =J70/4 -> 1.25 | L70: =F70-K70 -> -1.25
A71: 3 | B71: Basic Text - Gift Edition | D71: ='الصادر بعد الجرد'!Y71 -> 0 | E71: ='الوارد بعد الجرد'!AC71 -> 0 | F71: =C71-D71+E71 -> 0 | G71: 1225 | H71: =G71*F71 -> 0 | J71: 4 | K71: =J71/4 -> 1 | L71: =F71-K71 -> -1
A72: 4 | B72: JFT - Reg Size | C72: 7 | D72: ='الصادر بعد الجرد'!Y72 -> 0 | E72: ='الوارد بعد الجرد'!AC72 -> 0 | F72: =C72-D72+E72 -> 7 | G72: 500 | H72: =G72*F72 -> 3500 | J72: 10 | K72: =J72/4 -> 2.5 | L72: =F72-K72 -> 4.5
A73: 5 | B73: JFT - Pocket Size | D73: ='الصادر بعد الجرد'!Y73 -> 0 | E73: ='الوارد بعد الجرد'!AC73 -> 0 | F73: =C73-D73+E73 -> 0 | G73: 520 | H73: =G73*F73 -> 0 | J73: 3 | K73: =J73/4 -> 0.75 | L73: =F73-K73 -> -0.75
A74: 6 | B74: JFT - Gift Edition | D74: ='الصادر بعد الجرد'!Y74 -> 0 | E74: ='الوارد بعد الجرد'!AC74 -> 0 | F74: =C74-D74+E74 -> 0 | G74: 980 | H74: =G74*F74 -> 0 | J74: 3 | K74: =J74/4 -> 0.75 | L74: =F74-K74 -> -0.75
A75: 7 | B75: How & Why - Reg Size | C75: 8 | D75: ='الصادر بعد الجرد'!Y75 -> 0 | E75: ='الوارد بعد الجرد'!AC75 -> 0 | F75: =C75-D75+E75 -> 8 | G75: 425 | H75: =G75*F75 -> 3400 | J75: 15 | K75: =J75/4 -> 3.75 | L75: =F75-K75 -> 4.25
A76: 8 | B76: How & Why - Pocket Size | D76: ='الصادر بعد الجرد'!Y76 -> 0 | E76: ='الوارد بعد الجرد'!AC76 -> 0 | F76: =C76-D76+E76 -> 0 | G76: 440 | H76: =G76*F76 -> 0 | J76: 3 | K76: =J76/4 -> 0.75 | L76: =F76-K76 -> -0.75
A77: 9 | B77: Sponsorship | C77: 24 | D77: ='الصادر بعد الجرد'!Y77 -> 0 | E77: ='الوارد بعد الجرد'!AC77 -> 0 | F77: =C77-D77+E77 -> 24 | G77: 500 | H77: =G77*F77 -> 12000 | J77: 3 | K77: =J77/4 -> 0.75 | L77: =F77-K77 -> 23.25
A78: 10 | B78: Sponsorship - Gift Edition | C78: 7 | D78: ='الصادر بعد الجرد'!Y78 -> 0 | E78: ='الوارد بعد الجرد'!AC78 -> 0 | F78: =C78-D78+E78 -> 7 | G78: 980 | H78: =G78*F78 -> 6860 | J78: 1 | K78: =J78/4 -> 0.25 | L78: =F78-K78 -> 6.75
A79: 11 | B79: Step Working Guide | C79: 8 | D79: ='الصادر بعد الجرد'!Y79 -> 0 | E79: ='الوارد بعد الجرد'!AC79 -> 0 | F79: =C79-D79+E79 -> 8 | G79: 400 | H79: =G79*F79 -> 3200 | J79: 15 | K79: =J79/4 -> 3.75 | L79: =F79-K79 -> 4.25
A80: 12 | B80: Introductory Guide to NA | C80: 21 | D80: ='الصادر بعد الجرد'!Y80 -> 7 | E80: ='الوارد بعد الجرد'!AC80 -> 0 | F80: =C80-D80+E80 -> 14 | G80: 85 | H80: =G80*F80 -> 1190 | J80: 15 | K80: =J80/4 -> 3.75 | L80: =F80-K80 -> 10.25
A81: 13 | B81: Living Clean | C81: 14 | D81: ='الصادر بعد الجرد'!Y81 -> 0 | E81: ='الوارد بعد الجرد'!AC81 -> 0 | F81: =C81-D81+E81 -> 14 | G81: 545 | H81: =G81*F81 -> 7630 | J81: 10 | K81: =J81/4 -> 2.5 | L81: =F81-K81 -> 11.5
A82: 14 | B82: Guiding Principle | C82: 9 | D82: ='الصادر بعد الجرد'!Y82 -> 0 | E82: ='الوارد بعد الجرد'!AC82 -> 0 | F82: =C82-D82+E82 -> 9 | G82: 610 | H82: =G82*F82 -> 5490 | J82: 10 | K82: =J82/4 -> 2.5 | L82: =F82-K82 -> 6.5 | M82: يوجد كتاب في لجنة الادبيات زيادة وتم التعديل
A83: 15 | B83: Spiritual Principle A Day | C83: 26 | D83: ='الصادر بعد الجرد'!Y83 -> 0 | E83: ='الوارد بعد الجرد'!AC83 -> 0 | F83: =C83-D83+E83 -> 26 | G83: 610 | H83: =G83*F83 -> 15860 | J83: 40 | K83: =J83/4 -> 10 | L83: =F83-K83 -> 16
A84: 16 | B84: Miracle Happens Hard | D84: ='الصادر بعد الجرد'!Y84 -> 0 | E84: ='الوارد بعد الجرد'!AC84 -> 0 | F84: =C84-D84+E84 -> 0 | G84: 980 | H84: =G84*F84 -> 0 | J84: 1 | K84: =J84/4 -> 0.25 | L84: =F84-K84 -> -0.25
A85: 17 | B85: Commemorative Living Clean | D85: ='الصادر بعد الجرد'!Y85 -> 0 | E85: ='الوارد بعد الجرد'!AC85 -> 0 | F85: =C85-D85+E85 -> 0 | G85: 700 | H85: =G85*F85 -> 0 | J85: 3 | K85: =J85/4 -> 0.75 | L85: =F85-K85 -> -0.75
A86: 18 | B86: Guiding Principles Special Edition | D86: ='الصادر بعد الجرد'!Y86 -> 0 | E86: ='الوارد بعد الجرد'!AC86 -> 0 | F86: =C86-D86+E86 -> 0 | H86: =G86*F86 -> 0 | K86: =J86/4 -> 0 | L86: =F86-K86 -> 0
A87: 19 | B87: SPAD Special Edition | C87: 0 | D87: ='الصادر بعد الجرد'!Y87 -> 0 | E87: ='الوارد بعد الجرد'!AC87 -> 0 | F87: =C87-D87+E87 -> 0 | G87: 1640 | H87: =G87*F87 -> 0 | J87: 3 | K87: =J87/4 -> 0.75 | L87: =F87-K87 -> -0.75
A88: 20 | B88: JFT Journal | D88: ='الصادر بعد الجرد'!Y88 -> 0 | E88: ='الوارد بعد الجرد'!AC88 -> 0 | F88: =C88-D88+E88 -> 0 | G88: 695 | H88: =G88*F88 -> 0 | J88: 10 | K88: =J88/4 -> 2.5 | L88: =F88-K88 -> -2.5
A89: 21 | B89: NA the Survival Kit | C89: 4 | D89: ='الصادر بعد الجرد'!Y89 -> 0 | E89: ='الوارد بعد الجرد'!AC89 -> 0 | F89: =C89-D89+E89 -> 4 | G89: 730 | H89: =G89*F89 -> 2920
A90: 22 | B90: The Basic Library | D90: ='الصادر بعد الجرد'!Y90 -> 0 | E90: ='الوارد بعد الجرد'!AC90 -> 0 | F90: =C90-D90+E90 -> 0 | G90: 2340 | H90: =G90*F90 -> 0 | J90: 1 | K90: =J90/4 -> 0.25 | L90: =F90-K90 -> -0.25
B92: English IP (s)
A93: 1 | B93: For the Newcomer | C93: 14 | D93: ='الصادر بعد الجرد'!Y93 -> 0 | E93: ='الوارد بعد الجرد'!AC93 -> 0 | F93: =C93-D93+E93 -> 14 | G93: 10 | H93: =G93*F93 -> 140 | I93: 25 | J93: 30
A94: 2 | B94: Welcome to NA | D94: ='الصادر بعد الجرد'!Y94 -> 0 | E94: ='الوارد بعد الجرد'!AC94 -> 0 | F94: =C94-D94+E94 -> 0 | G94: 10 | H94: =G94*F94 -> 0
A95: 3 | B95: A resource in your community | C95: 2 | D95: ='الصادر بعد الجرد'!Y95 -> 0 | E95: ='الوارد بعد الجرد'!AC95 -> 0 | F95: =C95-D95+E95 -> 2 | G95: 10 | H95: =G95*F95 -> 20
A96: 4 | B96: Accessibility for Those with Additional Needs | C96: 16 | D96: ='الصادر بعد الجرد'!Y96 -> 0 | E96: ='الوارد بعد الجرد'!AC96 -> 0 | F96: =C96-D96+E96 -> 16 | G96: 10 | H96: =G96*F96 -> 160
A97: 5 | B97: Am I an Addict ? | D97: ='الصادر بعد الجرد'!Y97 -> 0 | E97: ='الوارد بعد الجرد'!AC97 -> 0 | F97: =C97-D97+E97 -> 0 | G97: 10 | H97: =G97*F97 -> 0
A98: 6 | B98: Another Look | C98: 47 | D98: ='الصادر بعد الجرد'!Y98 -> 0 | E98: ='الوارد بعد الجرد'!AC98 -> 0 | F98: =C98-D98+E98 -> 47 | G98: 10 | H98: =G98*F98 -> 470
A99: 7 | B99: Behind the Walls | C99: 10 | D99: ='الصادر بعد الجرد'!Y99 -> 0 | E99: ='الوارد بعد الجرد'!AC99 -> 0 | F99: =C99-D99+E99 -> 10 | G99: 40 | H99: =G99*F99 -> 400
A100: 8 | B100: By Young Addicts for Young Addicts | C100: 7 | D100: ='الصادر بعد الجرد'!Y100 -> 0 | E100: ='الوارد بعد الجرد'!AC100 -> 0 | F100: =C100-D100+E100 -> 7 | G100: 10 | H100: =G100*F100 -> 70
A101: 9 | B101: Disruptive & Violent | C101: 7 | D101: ='الصادر بعد الجرد'!Y101 -> 0 | E101: ='الوارد بعد الجرد'!AC101 -> 0 | F101: =C101-D101+E101 -> 7 | G101: 10 | H101: =G101*F101 -> 70
A102: 10 | B102: For the Parents or Guardians of Young People in NA | C102: 42 | D102: ='الصادر بعد الجرد'!Y102 -> 0 | E102: ='الوارد بعد الجرد'!AC102 -> 0 | F102: =C102-D102+E102 -> 42 | G102: 10 | H102: =G102*F102 -> 420
A103: 11 | B103: For Those in Treatment | C103: 72 | D103: ='الصادر بعد الجرد'!Y103 -> 0 | E103: ='الوارد بعد الجرد'!AC103 -> 0 | F103: =C103-D103+E103 -> 72 | G103: 10 | H103: =G103*F103 -> 720
A104: 12 | B104: Funding NA Services | C104: 44 | D104: ='الصادر بعد الجرد'!Y104 -> 0 | E104: ='الوارد بعد الجرد'!AC104 -> 0 | F104: =C104-D104+E104 -> 44 | G104: 10 | H104: =G104*F104 -> 440
A105: 13 | B105: Group Business | C105: 9 | D105: ='الصادر بعد الجرد'!Y105 -> 0 | E105: ='الوارد بعد الجرد'!AC105 -> 0 | F105: =C105-D105+E105 -> 9 | G105: 10 | H105: =G105*F105 -> 90
A106: 14 | B106: Hospitals and Institutions Service and the NA member | C106: 48 | D106: ='الصادر بعد الجرد'!Y106 -> 0 | E106: ='الوارد بعد الجرد'!AC106 -> 0 | F106: =C106-D106+E106 -> 48 | G106: 10 | H106: =G106*F106 -> 480
A107: 15 | B107: In Time of Illness | D107: ='الصادر بعد الجرد'!Y107 -> 0 | E107: ='الوارد بعد الجرد'!AC107 -> 0 | F107: =C107-D107+E107 -> 0 | G107: 135 | H107: =G107*F107 -> 0
A108: 16 | B108: Introduction to NA Meetings | D108: ='الصادر بعد الجرد'!Y108 -> 0 | E108: ='الوارد بعد الجرد'!AC108 -> 0 | F108: =C108-D108+E108 -> 0 | G108: 10 | H108: =G108*F108 -> 0
A109: 17 | B109: Just For Today (IP) | C109: 110 | D109: ='الصادر بعد الجرد'!Y109 -> 0 | E109: ='الوارد بعد الجرد'!AC109 -> 0 | F109: =C109-D109+E109 -> 110 | G109: 10 | H109: =G109*F109 -> 1100
A110: 18 | B110: Living the program | D110: ='الصادر بعد الجرد'!Y110 -> 0 | E110: ='الوارد بعد الجرد'!AC110 -> 0 | F110: =C110-D110+E110 -> 0 | G110: 10 | H110: =G110*F110 -> 0
A111: 19 | B111: Money Matters Self-Support in NA | C111: 41 | D111: ='الصادر بعد الجرد'!Y111 -> 0 | E111: ='الوارد بعد الجرد'!AC111 -> 0 | F111: =C111-D111+E111 -> 41 | G111: 10 | H111: =G111*F111 -> 410
A112: 20 | B112: NA Groups & Medication | C112: 134 | D112: ='الصادر بعد الجرد'!Y112 -> 0 | E112: ='الوارد بعد الجرد'!AC112 -> 0 | F112: =C112-D112+E112 -> 134 | G112: 10 | H112: =G112*F112 -> 1340
A113: 21 | B113: One Addict’s Experience with Acceptance, Faith, and Commitment | C113: 39 | D113: ='الصادر بعد الجرد'!Y113 -> 0 | E113: ='الوارد بعد الجرد'!AC113 -> 0 | F113: =C113-D113+E113 -> 39 | G113: 10 | H113: =G113*F113 -> 390
...

Sheet الصادر بعد الجرد
A1: البند | E1: lit comt | F1: lit comt | G1: lit comt | H1: lit comt | I1: lit comt | J1: karnaval upper egypt | K1: Lit comt | L1: lit comt | M1: Lit Comt | N1: lit comt | O1: Lit Comt | Y1: إجمالي الصادر
A2: التاريخ | E2: 46362 | F2: 31-7/2026
B3: code | C3: book in english | D3: الكتب
A4: 1 | D4: النص الاساسى | E4: 150 | Y4: =SUM(E4:X4) -> 150
A5: 2 | D5: إنه يعمل - كيف ولماذا | E5: 50 | Y5: =SUM(E5:X5) -> 50
A6: 3 | D6: دليل العمل بالخطوات | E6: 150 | Y6: =SUM(E6:X6) -> 150
A7: 4 | D7: كتاب لليوم فقط | E7: 40 | Y7: =SUM(E7:X7) -> 40
A8: 5 | D8: الدليل التمهيدى | Y8: =SUM(E8:X8) -> 0
A9: 6 | D9: روح تقاليدنا | E9: 40 | Y9: =SUM(E9:X9) -> 40
A10: 7 | D10: living clean | E10: 60 | Y10: =SUM(E10:X10) -> 60
A11: 8 | D11: النص الاساسى (جيب) | Y11: =SUM(E11:X11) -> 0
A12: 9 | D12: إنة يعمل - كيف ولماذا (جيب) | Y12: =SUM(E12:X12) -> 0
A13: 10 | D13: دليل العمل بالخطوات (جيب) | Y13: =SUM(E13:X13) -> 0
A14: 11 | D14: كتاب لليوم فقط (جيب) | Y14: =SUM(E14:X14) -> 0
A15: 12 | D15: النص الاساسى (تذكاري) | Y15: =SUM(E15:X15) -> 0
A16: 13 | D16: أنة يعمل - كيف ولماذا (تذكاري) | Y16: =SUM(E16:X16) -> 0
A17: 14 | D17: دليل عمل الخطوات (تذكاري) | Y17: =SUM(E17:X17) -> 0
A18: 15 | D18: كتاب لليوم فقط (تذكاري) | Y18: =SUM(E18:X18) -> 0
B19: code | C19: IP in english | D19: الكتيبات (IP) | Y19: =SUM(E19:X19) -> 0
A20: 1 | D20: للعضو الجديد | E20: 248 | Y20: =SUM(E20:X20) -> 248
A21: 2 | D21: هل انا مدمن | E21: 500 | Y21: =SUM(E21:X21) -> 500
A22: 3 | D22: مرحبا بك فى زمالة م.م. | F22: 100 | Y22: =SUM(E22:X22) -> 100 | AA22: 2927
A23: 4 | D23: لليوم فقط | Y23: =SUM(E23:X23) -> 0 | AA23: =AA22-Y23 -> 2927
A24: 5 | D24: التوجية | E24: 500 | Y24: =SUM(E24:X24) -> 500 | Z24: there was 300 ip delivered at october to lit sub comt so I add them at november
A25: 6 | D25: نظرة أخرى | Y25: =SUM(E25:X25) -> 0
A26: 7 | D26: التعافى والانتكاس | Y26: =SUM(E26:X26) -> 0
A27: 8 | D27: تقبل الذات | Y27: =SUM(E27:X27) -> 0
A28: 9 | D28: مثلث الهاجس الذاتي | Y28: =SUM(E28:X28) -> 0
A29: 10 | D29: مقدمة لاجتماعات زمالة م.م | Y29: =SUM(E29:X29) -> 0
A30: 11 | D30: من - ماذا - كيف ولماذا | Y30: =SUM(E30:X30) -> 0
A31: 12 | D31: تجربة مدمن مع التقبل والإيمان والالتزام | Y31: =SUM(E31:X31) -> 0
A32: 13 | D32: البقاء ممتنعا في الخارج | Y32: =SUM(E32:X32) -> 0
A33: 14 | D33: رسالة لمن هم بالمصحات | Y33: =SUM(E33:X33) -> 0
A34: 15 | D34: التواصل الاجتماعى | Y34: =SUM(E34:X34) -> 0
A35: 16 | D35: الخدم الموثوق بهم | Y35: =SUM(E35:X35) -> 0
A36: 17 | D36: الامور المالية | Y36: =SUM(E36:X36) -> 0
... A38: 19 | D38: السلوك المعيق | Y38: =SUM(E38:X38) -> 0
A39: 20 | D39: المجموعة | E39: 500 | Y39: =SUM(E39:X39) -> 500
A40: 21 | D40: معايشة البرنامج | Y40: =SUM(E40:X40) -> 0
A41: 22 | D41: المنعزل - البقاء ممتنعاً في الخارج | Y41: =SUM(E41:X41) -> 0
A42: 23 | D42: من المدمنين الشباب إلى المدمنين الشباب | Y42: =SUM(E42:X42) -> 0
A43: 24 | D43: للآباء أو أولياء أمور المدمنين الشباب | Y43: =SUM(E43:X43) -> 0
A44: 25 | D44: امكانية الوصول لذوي الاحتيجات | Y44: =SUM(E44:X44) -> 0
Y45: =SUM(E45:X45) -> 0
B46: code | D46: الشيبات Chips | Y46: =SUM(E46:X46) -> 0
A47: 1 | D47: Welcome / White | Y47: =SUM(E47:X47) -> 0
A48: 2 | D48: 30 Days / Orange | E48: 200 | Y48: =SUM(E48:X48) -> 200
A49: 3 | D49: 60 Days / Green | E49: 200 | Y49: =SUM(E49:X49) -> 200
A50: 4 | D50: 90 Days / Red | E50: 200 | Y50: =SUM(E50:X50) -> 200
A51: 5 | D51: 6 Months / Blue | E51: 200 | Y51: =SUM(E51:X51) -> 200
A52: 6 | D52: 9 Months / Yellow | E52: 200 | Y52: =SUM(E52:X52) -> 200
A53: 7 | D53: 1 Year / Moonglow | E53: 200 | Y53: =SUM(E53:X53) -> 200
A54: 8 | D54: 18 Months / Grey | E54: 200 | Y54: =SUM(E54:X54) -> 200
A55: 9 | D55: Muiltple Years / Black | E55: 138 | Y55: =SUM(E55:X55) -> 138
Y56: =SUM(E56:X56) -> 0
D57: Name Key Tag to be sold at event | Y57: =SUM(E57:X57) -> 0
D58: Name tag Welcome / White | Y58: =SUM(E58:X58) -> 0
D59: Name tag 30 Days / Orange | Y59: =SUM(E59:X59) -> 0
D60: Name tag 60 Days / Green | Y60: =SUM(E60:X60) -> 0
D61: Name tag 90 Days / Red | Y61: =SUM(E61:X61) -> 0
D62: Name tag 6 Months / Blue | Y62: =SUM(E62:X62) -> 0
D63: Name tag 9 Months / Yellow | Y63: =SUM(E63:X63) -> 0
D64: Name tag 1 Year / Moonglow | Y64: =SUM(E64:X64) -> 0
D65: Name tag 18 Months / Grey | Y65: =SUM(E65:X65) -> 0
D66: Name tag Muiltple Years / Black | Y66: =SUM(E66:X66) -> 0
Y67: =SUM(E67:X67) -> 0
B68: code | D68: English Books | Y68: =SUM(E68:X68) -> 0
A69: 1 | D69: Basic Text - Reg Size | Y69: =SUM(E69:X69) -> 0
A70: 2 | D70: Basic Text - Pocket Size | Y70: =SUM(E70:X70) -> 0
A71: 3 | D71: Basic Text - Gift Edition | Y71: =SUM(E71:X71) -> 0
A72: 4 | D72: JFT - Reg Size | Y72: =SUM(E72:X72) -> 0
A73: 5 | D73: JFT - Pocket Size | Y73: =SUM(E73:X73) -> 0
A74: 6 | D74: JFT - Gift Edition | Y74: =SUM(E74:X74) -> 0
A75: 7 | D75: How & Why - Reg Size | Y75: =SUM(E75:X75) -> 0
A76: 8 | D76: How & Why - Pocket Size | Y76: =SUM(E76:X76) -> 0
A77: 9 | D77: Sponsorship | Y77: =SUM(E77:X77) -> 0
A78: 10 | D78: Sponsorship - Gift Edition | Y78: =SUM(E78:X78) -> 0
A79: 11 | D79: Step Working Guide | Y79: =SUM(E79:X79) -> 0
A80: 12 | D80: Introductory Guide to NA | F80: 7 | Y80: =SUM(E80:X80) -> 7
A81: 13 | D81: Living Clean | Y81: =SUM(E81:X81) -> 0
A82: 14 | D82: Guiding Principle | Y82: =SUM(E82:X82) -> 0
A83: 15 | D83: Spiritual Principle A Day | Y83: =SUM(E83:X83) -> 0
A84: 16 | D84: Miracle Happens Hard | Y84: =SUM(E84:X84) -> 0
A85: 17 | D85: Commemorative Living Clean | Y85: =SUM(E85:X85) -> 0
A86: 18 | D86: Guiding Principles Special Edition | Y86: =SUM(E86:X86) -> 0
A87: 19 | D87: SPAD Special Edition | Y87: =SUM(E87:X87) -> 0
A88: 20 | D88: JFT Journal | Y88: =SUM(E88:X88) -> 0
A89: 21 | D89: NA the Survival Kit | Y89: =SUM(E89:X89) -> 0
A90: 22 | D90: The Basic Library | Y90: =SUM(E90:X90) -> 0
Y91: =SUM(E91:X91) -> 0
B92: code | D92: English IP (s) | Y92: =SUM(E92:X92) -> 0
A93: 1 | D93: For the Newcomer | Y93: =SUM(E93:X93) -> 0
A94: 2 | D94: Welcome to NA | Y94: =SUM(E94:X94) -> 0
A95: 3 | D95: A resource in your community | Y95: =SUM(E95:X95) -> 0
A96: 4 | D96: Accessibility for Those with Additional Needs | Y96: =SUM(E96:X96) -> 0
A97: 5 | D97: Am I an Addict ? | Y97: =SUM(E97:X97) -> 0
A98: 6 | D98: Another Look | Y98: =SUM(E98:X98) -> 0
A99: 7 | D99: Behind the Walls | Y99: =SUM(E99:X99) -> 0
A100: 8 | D100: By Young Addicts for Young Addicts | Y100: =SUM(E100:X100) -> 0
A101: 9 | D101: Disruptive & Violent | Y101: =SUM(E101:X101) -> 0
...

Sheet Inventory 12-6-2026
A11: الكتب | C11: الرصيد الحالي | D11: Count | E11: differnce | F11: Remarks
A12: 1 | B12: النص الاساسى | C12: 255 | D12: 255 | E12: =D12-C12 -> 0
A13: 2 | B13: إنه يعمل - كيف ولماذا | C13: 355 | D13: 355 | E13: =D13-C13 -> 0
A14: 3 | B14: دليل العمل بالخطوات | C14: 50 | D14: 100 | E14: =D14-C14 -> 50 | F14: there is wrong input when we received it 24/1/2026
A15: 4 | B15: كتاب لليوم فقط | C15: 525 | D15: 525 | E15: =D15-C15 -> 0
A16: 5 | B16: الدليل التمهيدى | C16: 377 | D16: 377 | E16: =D16-C16 -> 0
A17: 6 | B17: روح تقاليدنا | C17: 907 | D17: 907 | E17: =D17-C17 -> 0
A18: 7 | B18: living clean | C18: 940 | D18: 940 | E18: =D18-C18 -> 0
A19: 8 | B19: النص الاساسى (جيب) | C19: 0 | E19: =D19-C19 -> 0
A20: 9 | B20: إنة يعمل - كيف ولماذا (جيب) | C20: 0 | E20: =D20-C20 -> 0
A21: 10 | B21: دليل العمل بالخطوات (جيب) | C21: 0 | E21: =D21-C21 -> 0
A22: 11 | B22: كتاب لليوم فقط (جيب) | C22: 0 | E22: =D22-C22 -> 0
A23: 12 | B23: النص الاساسى (تذكاري) | C23: 0 | E23: =D23-C23 -> 0
A24: 13 | B24: أنة يعمل - كيف ولماذا (تذكاري) | C24: 4 | D24: 4 | E24: =D24-C24 -> 0
A25: 14 | B25: دليل عمل الخطوات (تذكاري) | C25: 4 | D25: 4 | E25: =D25-C25 -> 0 | F25: need to be trough as old printing
A26: 15 | B26: كتاب لليوم فقط (تذكاري) | C26: 0 | E26: =D26-C26 -> 0
B27: الكتيبات (IP) | E27: =D27-C27 -> 0
A28: 1 | B28: للعضو الجديد | C28: 1248 | D28: 1248 | E28: =D28-C28 -> 0
A29: 2 | B29: هل انا مدمن | C29: 0 | E29: =D29-C29 -> 0
A30: 3 | B30: مرحبا بك فى زمالة م.م. | C30: 100 | D30: 100 | E30: =D30-C30 -> 0
A31: 4 | B31: لليوم فقط | C31: 1427 | D31: 1426 | E31: =D31-C31 -> -1 | F31: input wrong Lit didn’t receive 300 written wrong at paper of receiving no this number
A32: 5 | B32: التوجية | C32: 401 | D32: 401 | E32: =D32-C32 -> 0
A33: 6 | B33: نظرة أخرى | C33: 2124 | D33: 2124 | E33: =D33-C33 -> 0
A34: 7 | B34: التعافى والانتكاس | C34: 967 | D34: 967 | E34: =D34-C34 -> 0
A35: 8 | B35: تقبل الذات | C35: 529 | D35: 529 | E35: =D35-C35 -> 0
A36: 9 | B36: مثلث الهاجس الذاتي | C36: 405 | D36: 400 | E36: =D36-C36 -> -5
A37: 10 | B37: مقدمة لاجتماعات زمالة م.م | C37: -100 | D37: 3100 | E37: =D37-C37 -> 3200 | F37: need to burn as wrong
A38: 11 | B38: من - ماذا - كيف ولماذا | C38: 375 | D38: 375 | E38: =D38-C38 -> 0
A39: 12 | B39: تجربة مدمن مع التقبل والإيمان والالتزام | C39: 850 | D39: 850 | E39: =D39-C39 -> 0
A40: 13 | B40: البقاء ممتنعا في الخارج | C40: 325 | D40: 345 | E40: =D40-C40 -> 20
A41: 14 | B41: رسالة لمن هم بالمصحات | C41: 575 | D41: 575 | E41: =D41-C41 -> 0
A42: 15 | B42: التواصل الاجتماعى | C42: 200 | D42: 200 | E42: =D42-C42 -> 0
A43: 16 | B43: الخدم الموثوق بهم | C43: 390 | D43: 390 | E43: =D43-C43 -> 0
A44: 17 | B44: الامور المالية | C44: 350 | D44: 350 | E44: =D44-C44 -> 0
A45: 18 | B45: تمويل الخدمات | C45: 490 | D45: 490 | E45: =D45-C45 -> 0
A46: 19 | B46: السلوك المعيق | C46: 1246 | D46: 1245 | E46: =D46-C46 -> -1
A47: 20 | B47: المجموعة | C47: 0 | D47: 0 | E47: =D47-C47 -> 0
A48: 21 | B48: معايشة البرنامج | C48: 270 | D48: 270 | E48: =D48-C48 -> 0
A49: 22 | B49: المنعزل - البقاء ممتنعاً | C49: 294 | D49: 294 | E49: =D49-C49 -> 0
... A52: 25 | B52: امكانية الوصول لذوي الاحتيجات | C52: 380 | D52: 380 | E52: =D52-C52 -> 0
E53: =D53-C53 -> 0
B54: الشيبات Chips | E54: =D54-C54 -> 0
A55: 1 | B55: Welcome / White | C55: 0 | D55: 0 | E55: =D55-C55 -> 0
A56: 2 | B56: 30 Days / Orange | C56: 906 | D56: 906 | E56: =D56-C56 -> 0
A57: 3 | B57: 60 Days / Green | C57: 844 | D57: 865 | E57: =D57-C57 -> 21
A58: 4 | B58: 90 Days / Red | C58: 571 | D58: 571 | E58: =D58-C58 -> 0
A59: 5 | B59: 6 Months / Blue | C59: 498 | D59: 498 | E59: =D59-C59 -> 0
A60: 6 | B60: 9 Months / Yellow | C60: 1318 | D60: 1318 | E60: =D60-C60 -> 0
A61: 7 | B61: 1 Year / Moonglow | C61: 886 | D61: 906 | E61: =D61-C61 -> 20
A62: 8 | B62: 18 Months / Grey | C62: 1289 | D62: 1289 | E62: =D62-C62 -> 0
A63: 9 | B63: Muiltple Years / Black | C63: 138 | D63: 138 | E63: =D63-C63 -> 0
E64: =D64-C64 -> 0
B65: Name Key Tag to be sold at event | E65: =D65-C65 -> 0
A66: 1 | B66: Name tag Welcome / White | C66: 197 | D66: 197 | E66: =D66-C66 -> 0
A67: 2 | B67: Name tag 30 Days / Orange | C67: 205 | D67: 205 | E67: =D67-C67 -> 0
A68: 3 | B68: Name tag 60 Days / Green | C68: 208 | D68: 208 | E68: =D68-C68 -> 0
A69: 4 | B69: Name tag 90 Days / Red | C69: 200 | D69: 200 | E69: =D69-C69 -> 0
A70: 5 | B70: Name tag 6 Months / Blue | C70: 204 | D70: 204 | E70: =D70-C70 -> 0
A71: 6 | B71: Name tag 9 Months / Yellow | C71: 206 | D71: 206 | E71: =D71-C71 -> 0
A72: 7 | B72: Name tag 1 Year / Moonglow | C72: 208 | D72: 198 | E72: =D72-C72 -> -10
A73: 8 | B73: Name tag 18 Months / Grey | C73: 205 | D73: 202 | E73: =D73-C73 -> -3
A74: 9 | B74: Name tag Muiltple Years / Black | C74: 201 | D74: 201 | E74: =D74-C74 -> 0
E75: =D75-C75 -> 0
B76: English Books | E76: =D76-C76 -> 0
A77: 1 | B77: Basic Text - Reg Size | C77: 28 | D77: 28 | E77: =D77-C77 -> 0
A78: 2 | B78: Basic Text - Pocket Size | C78: 0 | E78: =D78-C78 -> 0
A79: 3 | B79: Basic Text - Gift Edition | C79: 0 | E79: =D79-C79 -> 0
A80: 4 | B80: JFT - Reg Size | C80: 7 | D80: 7 | E80: =D80-C80 -> 0
A81: 5 | B81: JFT - Pocket Size | C81: 0 | E81: =D81-C81 -> 0
A82: 6 | B82: JFT - Gift Edition | C82: 0 | E82: =D82-C82 -> 0
A83: 7 | B83: How & Why - Reg Size | C83: 8 | D83: 8 | E83: =D83-C83 -> 0
A84: 8 | B84: How & Why - Pocket Size | C84: 0 | E84: =D84-C84 -> 0
A85: 9 | B85: Sponsorship | C85: 23 | D85: 24 | E85: =D85-C85 -> 1
A86: 10 | B86: Sponsorship - Gift Edition | C86: 7 | D86: 7 | E86: =D86-C86 -> 0
A87: 11 | B87: Step Working Guide | C87: 5 | D87: 8 | E87: =D87-C87 -> 3
A88: 12 | B88: Introductory Guide to NA | C88: 21 | D88: 21 | E88: =D88-C88 -> 0
A89: 13 | B89: Living Clean | C89: 14 | D89: 14 | E89: =D89-C89 -> 0
A90: 14 | B90: Guiding Principle | C90: 9 | D90: 9 | E90: =D90-C90 -> 0
A91: 15 | B91: Spiritual Principle A Day | C91: 21 | D91: 26 | E91: =D91-C91 -> 5
A92: 16 | B92: Miracle Happens Hard | C92: 0 | E92: =D92-C92 -> 0
A93: 17 | B93: Commemorative Living Clean | C93: 0 | E93: =D93-C93 -> 0
A94: 18 | B94: Guiding Principles Special Edition | C94: 0 | E94: =D94-C94 -> 0
A95: 19 | B95: SPAD Special Edition | C95: 5 | D95: 0 | E95: =D95-C95 -> -5
A96: 20 | B96: JFT Journal | C96: 0 | E96: =D96-C96 -> 0
A97: 21 | B97: NA the Survival Kit | C97: 4 | D97: 4 | E97: =D97-C97 -> 0
A98: 22 | B98: The Basic Library | C98: 0 | E98: =D98-C98 -> 0
E99: =D99-C99 -> 0
B100: English IP (s) | E100: =D100-C100 -> 0
A101: 1 | B101: For the Newcomer | C101: 14 | D101: 14 | E101: =D101-C101 -> 0
A102: 2 | B102: Welcome to NA | C102: 0 | E102: =D102-C102 -> 0
A103: 3 | B103: A resource in your community | C103: 2 | D103: 2 | E103: =D103-C103 -> 0
A104: 4 | B104: Accessibility for Those with Additional Needs | C104: 16 | D104: 16 | E104: =D104-C104 -> 0
A105: 5 | B105: Am I an Addict ? | C105: 0 | E105: =D105-C105 -> 0
A106: 6 | B106: Another Look | C106: 47 | D106: 47 | E106: =D106-C106 -> 0
A107: 7 | B107: Behind the Walls | C107: 10 | D107: 10 | E107: =D107-C107 -> 0
A108: 8 | B108: By Young Addicts for Young Addicts | C108: 7 | D108: 7 | E108: =D108-C108 -> 0
A109: 9 | B109: Disruptive & Violent | C109: 7 | D109: 7 | E109: =D109-C109 -> 0
A110: 10 | B110: For the Parents or Guardians of Young People in NA | C110: 42 | D110: 42 | E110: =D110-C110 -> 0
A111: 11 | B111: For Those in Treatment | C111: 72 | D111: 72 | E111: =D111-C111 -> 0
A112: 12 | B112: Funding NA Services | C112: 44 | D112: 44 | E112: =D112-C112 -> 0
...

Sheet الوارد بعد الجرد
A1: البند | E1: Lit Comt | AC1: إجمالي الوارد
A2: التاريخ | E2: 46362
B3: code | C3: book in english | D3: الكتب
A4: 1 | D4: النص الاساسى | E4: 100 | AC4: =SUM(E4:AB4) -> 100
A5: 2 | D5: إنه يعمل - كيف ولماذا | AC5: =SUM(E5:AB5) -> 0
A6: 3 | D6: دليل العمل بالخطوات | E6: 150 | AC6: =SUM(E6:AB6) -> 150
A7: 4 | D7: كتاب لليوم فقط | AC7: =SUM(E7:AB7) -> 0
A8: 5 | D8: الدليل التمهيدى | AC8: =SUM(E8:AB8) -> 0
A9: 6 | D9: روح تقاليدنا | AC9: =SUM(E9:AB9) -> 0
A10: 7 | D10: living clean arabic | AC10: =SUM(E10:AB10) -> 0
A11: 8 | D11: النص الاساسى (جيب) | AC11: =SUM(E11:AB11) -> 0
A12: 9 | D12: إنة يعمل - كيف ولماذا (جيب) | AC12: =SUM(E12:AB12) -> 0
A13: 10 | D13: دليل العمل بالخطوات (جيب) | AC13: =SUM(E13:AB13) -> 0
A14: 11 | D14: كتاب لليوم فقط (جيب) | AC14: =SUM(E14:AB14) -> 0
A15: 12 | D15: النص الاساسى (تذكاري) | AC15: =SUM(E15:AB15) -> 0
A16: 13 | D16: أنة يعمل - كيف ولماذا (تذكاري) | AC16: =SUM(E16:AB16) -> 0
A17: 14 | D17: دليل عمل الخطوات (تذكاري) | AC17: =SUM(E17:AB17) -> 0
A18: 15 | D18: كتاب لليوم فقط (تذكاري) | AC18: =SUM(E18:AB18) -> 0
B19: code | C19: IP | D19: الكتيبات (IP) | AC19: =SUM(E19:AB19) -> 0
A20: 1 | D20: للعضو الجديد | AC20: =SUM(E20:AB20) -> 0
A21: 2 | D21: هل انا مدمن | E21: 500 | AC21: =SUM(E21:AB21) -> 500
A22: 3 | D22: مرحبا بك فى زمالة م.م. | AC22: =SUM(E22:AB22) -> 0
A23: 4 | D23: لليوم فقط | AC23: =SUM(E23:AB23) -> 0
A24: 5 | D24: التوجية | E24: 500 | AC24: =SUM(E24:AB24) -> 500 | AD24: there was 300 ip delivered at october to lit sub comt so I add them at november
A25: 6 | D25: نظرة أخرى | AC25: =SUM(E25:AB25) -> 0
A26: 7 | D26: التعافى والانتكاس | AC26: =SUM(E26:AB26) -> 0
A27: 8 | D27: تقبل الذات | AC27: =SUM(E27:AB27) -> 0
A28: 9 | D28: مثلث الهاجس الذاتي | AC28: =SUM(E28:AB28) -> 0
A29: 10 | D29: مقدمة لاجتماعات زمالة م.م | AC29: =SUM(E29:AB29) -> 0
A30: 11 | D30: من - ماذا - كيف ولماذا | AC30: =SUM(E30:AB30) -> 0
A31: 12 | D31: تجربة مدمن مع التقبل والإيمان والالتزام | AC31: =SUM(E31:AB31) -> 0
A32: 13 | D32: البقاء ممتنعا في الخارج | AC32: =SUM(E32:AB32) -> 0
A33: 14 | D33: رسالة لمن هم بالمصحات | AC33: =SUM(E33:AB33) -> 0
A34: 15 | D34: التواصل الاجتماعى | AC34: =SUM(E34:AB34) -> 0
A35: 16 | D35: الخدم الموثوق بهم | AC35: =SUM(E35:AB35) -> 0
A36: 17 | D36: الامور المالية | AC36: =SUM(E36:AB36) -> 0
... A38: 19 | D38: السلوك المعيق | AC38: =SUM(E38:AB38) -> 0
A39: 20 | D39: المجموعة | E39: 500 | AC39: =SUM(E39:AB39) -> 500
A40: 21 | D40: معايشة البرنامج | AC40: =SUM(E40:AB40) -> 0
A41: 22 | D41: المنعزل - البقاء ممتنعاً في الخارج | AC41: =SUM(E41:AB41) -> 0
A42: 23 | D42: من المدمنين الشباب إلى المدمنين الشباب | AC42: =SUM(E42:AB42) -> 0
A43: 24 | D43: للآباء أو أولياء أمور المدمنين الشباب | AC43: =SUM(E43:AB43) -> 0
A44: 25 | D44: امكانية الوصول لذوي الاحتيجات | AC44: =SUM(E44:AB44) -> 0
AC45: =SUM(E45:AB45) -> 0
B46: code | D46: الشيبات Chips | AC46: =SUM(E46:AB46) -> 0
A47: 1 | D47: Welcome / White | AC47: =SUM(E47:AB47) -> 0
A48: 2 | D48: 30 Days / Orange | AC48: =SUM(E48:AB48) -> 0
A49: 3 | D49: 60 Days / Green | AC49: =SUM(E49:AB49) -> 0
A50: 4 | D50: 90 Days / Red | AC50: =SUM(E50:AB50) -> 0
A51: 5 | D51: 6 Months / Blue | AC51: =SUM(E51:AB51) -> 0
A52: 6 | D52: 9 Months / Yellow | AC52: =SUM(E52:AB52) -> 0
A53: 7 | D53: 1 Year / Moonglow | AC53: =SUM(E53:AB53) -> 0
A54: 8 | D54: 18 Months / Grey | AC54: =SUM(E54:AB54) -> 0
A55: 9 | D55: Muiltple Years / Black | AC55: =SUM(E55:AB55) -> 0
AC56: =SUM(E56:AB56) -> 0
D57: Name Key Tag to be sold at event | AC57: =SUM(E57:AB57) -> 0
A58: 1 | D58: Name tag Welcome / White | AC58: =SUM(E58:AB58) -> 0
A59: 2 | D59: Name tag 30 Days / Orange | AC59: =SUM(E59:AB59) -> 0
A60: 3 | D60: Name tag 60 Days / Green | AC60: =SUM(E60:AB60) -> 0
A61: 4 | D61: Name tag 90 Days / Red | AC61: =SUM(E61:AB61) -> 0
A62: 5 | D62: Name tag 6 Months / Blue | AC62: =SUM(E62:AB62) -> 0
A63: 6 | D63: Name tag 9 Months / Yellow | AC63: =SUM(E63:AB63) -> 0
A64: 7 | D64: Name tag 1 Year / Moonglow | AC64: =SUM(E64:AB64) -> 0
A65: 8 | D65: Name tag 18 Months / Grey | AC65: =SUM(E65:AB65) -> 0
A66: 9 | D66: Name tag Muiltple Years / Black | AC66: =SUM(E66:AB66) -> 0
AC67: =SUM(E67:AB67) -> 0
B68: code | D68: English Books | AC68: =SUM(E68:AB68) -> 0
A69: 1 | D69: Basic Text - Reg Size | AC69: =SUM(E69:AB69) -> 0
A70: 2 | D70: Basic Text - Pocket Size | AC70: =SUM(E70:AB70) -> 0
A71: 3 | D71: Basic Text - Gift Edition | AC71: =SUM(E71:AB71) -> 0
A72: 4 | D72: JFT - Reg Size | AC72: =SUM(E72:AB72) -> 0
A73: 5 | D73: JFT - Pocket Size | AC73: =SUM(E73:AB73) -> 0
A74: 6 | D74: JFT - Gift Edition | AC74: =SUM(E74:AB74) -> 0
A75: 7 | D75: How & Why - Reg Size | AC75: =SUM(E75:AB75) -> 0
A76: 8 | D76: How & Why - Pocket Size | AC76: =SUM(E76:AB76) -> 0
A77: 9 | D77: Sponsorship | AC77: =SUM(E77:AB77) -> 0
A78: 10 | D78: Sponsorship - Gift Edition | AC78: =SUM(E78:AB78) -> 0
A79: 11 | D79: Step Working Guide | AC79: =SUM(E79:AB79) -> 0
A80: 12 | D80: Introductory Guide to NA | AC80: =SUM(E80:AB80) -> 0
... A90: 22 | D90: The Basic Library | AC90: =SUM(E90:AB90) -> 0
AC91: =SUM(E91:AB91) -> 0
B92: code | D92: English IP (s) | AC92: =SUM(E92:AB92) -> 0
A93: 1 | D93: For the Newcomer | AC93: =SUM(E93:AB93) -> 0
A94: 2 | D94: Welcome to NA | AC94: =SUM(E94:AB94) -> 0
A95: 3 | D95: A resource in your community | AC95: =SUM(E95:AB95) -> 0
A96: 4 | D96: Accessibility for Those with Additional Needs | AC96: =SUM(E96:AB96) -> 0
A97: 5 | D97: Am I an Addict ? | AC97: =SUM(E97:AB97) -> 0
A98: 6 | D98: Another Look | AC98: =SUM(E98:AB98) -> 0
A99: 7 | D99: Behind the Walls | AC99: =SUM(E99:AB99) -> 0
A100: 8 | D100: By Young Addicts for Young Addicts | AC100: =SUM(E100:AB100) -> 0
A101: 9 | D101: Disruptive & Violent | AC101: =SUM(E101:AB101) -> 0
A102: 10 | D102: For the Parents or Guardians of Young People in NA | AC102: =SUM(E102:AB102) -> 0
A103: 11 | D103: For Those in Treatment | AC103: =SUM(E103:AB103) -> 0
A104: 12 | D104: Funding NA Services | AC104: =SUM(E104:AB104) -> 0
... A130: 38 | D130: Mental Health in Recovery | AC130: =SUM(E130:AB130) -> 0
AC131: =SUM(E131:AB131) -> 0
B132: code | D132: Readings القراءات | AC132: =SUM(E132:AB132) -> 0
A133: 1 | D133: مجموعة قراءات (عربي) | AC133: =SUM(E133:AB133) -> 0
A134: 2 | D134: مجموعة قراءات (انجليزي) | AC134: =SUM(E134:AB134) -> 0
AC135: =SUM(E135:AB135) -> 0
...

Sheet order received from WSO us 2024
A1: orders Febauary March April 2024 | C1: from WSO USA to Egypt | D1: Order 1
A2: description | C2: order pack | D2: from | E2: Received after Egyptian tax | F2: price/us$ | G2: price after discount/us$ | H2: Owing balance for WSO/US$ | I2: Differnce not received | L2: Received at Sofia 2024
A3: البيان | C3: الطلبية/من مكتب الخدمة العالمي | D3: من | E3: المستلم بعد الجمرك | F3: السعر/دولار امريكي | G3: نسبة الخصم ٥٠٪ | H3: سوف يتم دفعه الي مكتب الخدمة العالمي | I3: فرق المرسل/المستلم | L3: order to be delivered at sofia | M3: Code | N3: Descraption | O3: order | P3: from
A4: 1 | B4: Welcome / White | C4: =300+150+150 -> 600 | D4: WSO | E4: =148+147+146+147 -> 588 | F4: 0.4 | G4: =F4/2 -> 0.2 | H4: =G4*E4 -> 117.6 | I4: =E4-C4 -> -12 | L4: 1 | M4: 9603 | N4: sponsorship medallion & keychain | O4: 10 | P4: wso
A5: 2 | B5: 30 Days / Orange | C5: =300+150+150 -> 600 | D5: WSO | E5: =148+147+148+147 -> 590 | F5: 0.4 | G5: =F5/2 -> 0.2 | H5: =G5*E5 -> 118 | I5: =E5-C5 -> -10 | L5: 2 | M5: 9054 | N5: literature rack (wire 16 pocket) | O5: 1 | P5: wso
A6: 3 | B6: 60 Days / Green | C6: =300+150+150 -> 600 | D6: WSO | E6: =148+146+148+148 -> 590 | F6: 0.4 | G6: =F6/2 -> 0.2 | H6: =G6*E6 -> 118 | I6: =E6-C6 -> -10 | L6: 3 | M6: 6200 | N6: 1 year triplate ( purple/dark blue/black | O6: 2 | P6: wso
A7: 4 | B7: 90 Days / Red | C7: =300+150+150 -> 600 | D7: WSO | E7: =148+147+147+147 -> 589 | F7: 0.4 | G7: =F7/2 -> 0.2 | H7: =G7*E7 -> 117.8 | I7: =E7-C7 -> -11 | L7: 4 | M7: 6200 | N7: 4 years triplate | O7: 2 | P7: wso
A8: 5 | B8: 6 Months / Blue | C8: =300+150+150 -> 600 | D8: WSO | E8: =146+145+145+145 -> 581 | F8: 0.4 | G8: =F8/2 -> 0.2 | H8: =G8*E8 -> 116.2 | I8: =E8-C8 -> -19 | L8: 5 | M8: 6300 | N8: 10 years triplate | O8: 2 | P8: wso
A9: 6 | B9: 9 Months / Yellow | C9: =150+150+150 -> 450 | D9: WSO | E9: =145+145+145 -> 435 | F9: 0.4 | G9: =F9/2 -> 0.2 | H9: =G9*E9 -> 87 | I9: =E9-C9 -> -15 | L9: 6 | M9: 6300 | N9: etirnity triplate medallion | O9: 4 | P9: wso
A10: 7 | B10: 1 Year / Moonglow | C10: =150+150+150 -> 450 | D10: WSO | E10: =141+142+141 -> 424 | F10: 0.4 | G10: =F10/2 -> 0.2 | H10: =G10*E10 -> 84.8 | I10: =E10-C10 -> -26 | L10: 7 | M10: 6200 | N10: etirnity triplate medallion | O10: 3 | P10: wso
A11: 8 | B11: 18 Months / Grey | C11: =150+100 -> 250 | D11: WSO | E11: =149+99 -> 248 | F11: 0.4 | G11: =F11/2 -> 0.2 | H11: =G11*E11 -> 49.6 | I11: =E11-C11 -> -2 | L11: 8 | M11: GOLD | N11: etirnity triplate medallion | P11: wso
A12: 9 | B12: Multiple Years / Black | C12: =150+150+150 -> 450 | D12: WSO | E12: =146+147+147 -> 440 | F12: 0.4 | G12: =F12/2 -> 0.2 | H12: =G12*E12 -> 88 | I12: =E12-C12 -> -10 | L12: 9 | M12: 6800 | N12: etirnity triplate medallion | O12: 2 | P12: wso
A13: 10 | B13: SET OF ENGLISH READING | C13: 5 | D13: WSO | E13: 5 | F13: 1 | G13: =F13/2 -> 0.5 | H13: =G13*E13 -> 2.5 | I13: =E13-C13 -> 0 | L13: 10 | M13: 6090 | N13: keychain for etched medallion silver | O13: 5 | P13: wso
A14: 11 | B14: It Works: How and Why (Hard Cover) | C14: 2 | D14: WSO | E14: 2 | F14: 10.7 | G14: =F14/2 -> 5.35 | H14: =G14*E14 -> 10.7 | I14: =E14-C14 -> 0 | L14: 11 | M14: 6091 | N14: keychain for bronze- black | O14: 10 | P14: wso
A15: 12 | B15: Step Working Guide | C15: 5 | D15: WSO | E15: 5 | F15: 10.1 | G15: =F15/2 -> 5.05 | H15: =G15*E15 -> 25.25 | I15: =E15-C15 -> 0 | L15: 12 | M15: 6092 | N15: keychain for bronze- satin gold | O15: 10 | P15: wso
A16: 13 | B16: Large-Print It Works: How and Why | C16: 3 | D16: WSO | E16: 3 | F16: 10.7 | G16: =F16/2 -> 5.35 | H16: =G16*E16 -> 16.05 | I16: =E16-C16 -> 0 | L16: 13 | M16: 6903 | N16: keychain for bronze - bronze | O16: 10 | P16: wso
A17: 14 | B17: An Introductory Guide to NA | C17: 20 | D17: WSO | E17: 20 | F17: 2.1 | G17: =F17/2 -> 1.05 | H17: =G17*E17 -> 21 | I17: =E17-C17 -> 0
A18: Total | H18: =SUM(H4:H17) -> 972.5 | I18: =SUM(I4:I17) -> -115
A20: Order may June July 2024 | C20: from WSO USA to Egypt | D20: Orderv 2
B21: descraption | D21: order QTY | E21: Received after Egypatain tax | F21: price/us$ | I21: Differnce not received
A22: البيان | C22: الطلبية/من مكتب الخدمة العالمي | D22: من | E22: المستلم بعد الجمرك | F22: فرق المرسل/المستلم | I22: فرق المرسل/المستلم
A23: 1 | B23: Welcome / White | C23: chip | D23: 500 | E23: 493 | F23: =E23-D23 -> -7 | I23: =E23-D23 -> -7
A24: 2 | B24: 30 Days / Orange | C24: chip | D24: 500 | E24: 479 | F24: =E24-D24 -> -21 | I24: =E24-D24 -> -21
A25: 3 | B25: 60 Days / Green | C25: chip | D25: 500 | E25: 490 | F25: =E25-D25 -> -10 | I25: =E25-D25 -> -10
A26: 4 | B26: 90 Days / Red | C26: chip | D26: 1000 | E26: 969 | F26: =E26-D26 -> -31 | I26: =E26-D26 -> -31
A27: 5 | B27: 6 Months / Blue | C27: chip | D27: 250 | E27: 240 | F27: =E27-D27 -> -10 | I27: =E27-D27 -> -10
A28: 6 | B28: 9 Months / Yellow | C28: chip | D28: 450 | E28: 432 | F28: =E28-D28 -> -18 | I28: =E28-D28 -> -18
A29: 7 | B29: 1 Year / Moonglow | C29: chip | D29: 200 | E29: 193 | F29: =E29-D29 -> -7 | I29: =E29-D29 -> -7
A30: 8 | B30: 18 Months / Grey | C30: chip | D30: 200 | E30: 194 | F30: =E30-D30 -> -6 | I30: =E30-D30 -> -6
A31: 9 | B31: Muiltple Years / Black | C31: chip | D31: 206 | E31: 202 | F31: =E31-D31 -> -4 | I31: =E31-D31 -> -4
A32: 10 | B32: Basic Text - Reg Size | C32: book | D32: 10 | E32: 10 | F32: =E32-D32 -> 0 | I32: =E32-D32 -> 0
A33: 11 | B33: Step Working Guide | C33: book | D33: 15 | E33: 15 | F33: =E33-D33 -> 0 | I33: =E33-D33 -> 0
A34: 12 | B34: مجموعة قراءات (عربي) | C34: arabic reading | D34: 19 | E34: 19 | F34: =E34-D34 -> 0 | I34: =E34-D34 -> 0
A35: Total | I35: =SUM(I23:I34) -> -114
J47: Total
